LICENSE
MANIFEST.in
README.md
quicktest.py
settings_test.py
setup.py
django_vkontakte_wall_statistic.egg-info/PKG-INFO
django_vkontakte_wall_statistic.egg-info/SOURCES.txt
django_vkontakte_wall_statistic.egg-info/dependency_links.txt
django_vkontakte_wall_statistic.egg-info/not-zip-safe
django_vkontakte_wall_statistic.egg-info/requires.txt
django_vkontakte_wall_statistic.egg-info/top_level.txt
vkontakte_wall_statistic/__init__.py
vkontakte_wall_statistic/__init__.pyc
vkontakte_wall_statistic/admin.py
vkontakte_wall_statistic/admin.pyc
vkontakte_wall_statistic/factories.py
vkontakte_wall_statistic/factories.pyc
vkontakte_wall_statistic/models.py
vkontakte_wall_statistic/models.pyc
vkontakte_wall_statistic/tests.py
vkontakte_wall_statistic/tests.pyc
vkontakte_wall_statistic/views.py
vkontakte_wall_statistic/migrations/0001_initial.py
vkontakte_wall_statistic/migrations/0001_initial.pyc
vkontakte_wall_statistic/migrations/0002_auto__chg_field_poststatistic_reach_males_age_24_27__chg_field_poststa.py
vkontakte_wall_statistic/migrations/0002_auto__chg_field_poststatistic_reach_males_age_24_27__chg_field_poststa.pyc
vkontakte_wall_statistic/migrations/__init__.py
vkontakte_wall_statistic/migrations/__init__.pyc